bootstrap_forms/__init__.py
bootstrap_forms/admin.py
bootstrap_forms/apps.py
bootstrap_forms/models.py
bootstrap_forms/tests.py
bootstrap_forms/views.py
bootstrap_forms/bootstrap_forms/__init__.py
bootstrap_forms/bootstrap_forms/admin.py
bootstrap_forms/bootstrap_forms/apps.py
bootstrap_forms/bootstrap_forms/models.py
bootstrap_forms/bootstrap_forms/tests.py
bootstrap_forms/bootstrap_forms/views.py
bootstrap_forms/bootstrap_forms/migrations/__init__.py
bootstrap_forms/bootstrap_forms/templatetags/__init__.py
bootstrap_forms/bootstrap_forms/templatetags/bootstrap_forms_tags.py
bootstrap_forms/migrations/__init__.py
bootstrap_forms/templatetags/__init__.py
bootstrap_forms/templatetags/bootstrap_forms_tags.py
nvs_bootstrap_forms-0.1.dist-info/LICENSE.md
nvs_bootstrap_forms-0.1.dist-info/METADATA
nvs_bootstrap_forms-0.1.dist-info/WHEEL
nvs_bootstrap_forms-0.1.dist-info/top_level.txt
nvs_bootstrap_forms-0.1.dist-info/RECORD
